odoo/addons/product_packaging_unit_price_calculator/README.rst
odoo/addons/product_packaging_unit_price_calculator/__init__.py
odoo/addons/product_packaging_unit_price_calculator/__manifest__.py
odoo/addons/product_packaging_unit_price_calculator/i18n/ca.po
odoo/addons/product_packaging_unit_price_calculator/i18n/es.po
odoo/addons/product_packaging_unit_price_calculator/i18n/product_packaging_unit_price_calculator.pot
odoo/addons/product_packaging_unit_price_calculator/models/__init__.py
odoo/addons/product_packaging_unit_price_calculator/models/product.py
odoo/addons/product_packaging_unit_price_calculator/models/product_packaging.py
odoo/addons/product_packaging_unit_price_calculator/models/product_pricelist.py
odoo/addons/product_packaging_unit_price_calculator/models/product_supplierinfo.py
odoo/addons/product_packaging_unit_price_calculator/readme/CONTRIBUTORS.rst
odoo/addons/product_packaging_unit_price_calculator/readme/DESCRIPTION.rst
odoo/addons/product_packaging_unit_price_calculator/readme/USAGE.rst
odoo/addons/product_packaging_unit_price_calculator/static/description/icon.png
odoo/addons/product_packaging_unit_price_calculator/static/description/index.html
odoo/addons/product_packaging_unit_price_calculator/tests/__init__.py
odoo/addons/product_packaging_unit_price_calculator/tests/test_product_price_packaging_qty.py
odoo/addons/product_packaging_unit_price_calculator/views/product_packaging.xml
odoo/addons/product_packaging_unit_price_calculator/views/product_pricelist.xml
odoo/addons/product_packaging_unit_price_calculator/views/product_supplierinfo.xml
odoo/addons/product_packaging_unit_price_calculator/views/product_view.xml
odoo/addons/product_packaging_unit_price_calculator/wizards/__init__.py
odoo/addons/product_packaging_unit_price_calculator/wizards/product_package_price.py
odoo/addons/product_packaging_unit_price_calculator/wizards/product_package_price.xml
odoo13_addon_product_packaging_unit_price_calculator-13.0.1.0.2.dist-info/METADATA
odoo13_addon_product_packaging_unit_price_calculator-13.0.1.0.2.dist-info/WHEEL
odoo13_addon_product_packaging_unit_price_calculator-13.0.1.0.2.dist-info/top_level.txt
odoo13_addon_product_packaging_unit_price_calculator-13.0.1.0.2.dist-info/RECORD
