Metadata-Version: 2.1
Name: odoo13-addon-product-packaging-unit-price-calculator
Version: 13.0.1.0.2
Summary: Wizard to calculate a unit price from a packaging price
Home-page: https://www.camptocamp.com
Author: Camptocamp, Odoo Community Association (OCA)
Author-email: support@odoo-community.org
License: AGPL-3
Platform: UNKNOWN
Classifier: Programming Language :: Python
Classifier: Framework :: Odoo
Classifier: License :: OSI Approved :: GNU Affero General Public License v3
Requires-Python: >=3.5
Requires-Dist: odoo (<13.1dev,>=13.0a)
